puglang/__init__.py
puglang/pug.py
puglang/lang/__init__.py
puglang/lang/lexer.py
puglang/lang/parser.py
puglang/lang/token.py
puglang/lang/token_type.py
puglang-0.0.4.dist-info/LICENSE.txt
puglang-0.0.4.dist-info/METADATA
puglang-0.0.4.dist-info/WHEEL
puglang-0.0.4.dist-info/entry_points.txt
puglang-0.0.4.dist-info/top_level.txt
puglang-0.0.4.dist-info/RECORD
